Emma/__init__.py
Emma/emma.py
Emma/emma_deltas.py
Emma/emma_vis.py
Emma/emma_delta_libs/Delta.py
Emma/emma_delta_libs/FilePresenter.py
Emma/emma_delta_libs/FileSelector.py
Emma/emma_delta_libs/RootSelector.py
Emma/emma_delta_libs/__init__.py
Emma/emma_libs/__init__.py
Emma/emma_libs/categorisation.py
Emma/emma_libs/configuration.py
Emma/emma_libs/ghsConfiguration.py
Emma/emma_libs/ghsMapfileProcessor.py
Emma/emma_libs/ghsMapfileRegexes.py
Emma/emma_libs/mapfileProcessor.py
Emma/emma_libs/mapfileProcessorFactory.py
Emma/emma_libs/memoryEntry.py
Emma/emma_libs/memoryManager.py
Emma/emma_libs/memoryMap.py
Emma/emma_libs/specificConfiguration.py
Emma/emma_libs/specificConfigurationFactory.py
Emma/emma_vis_libs/__init__.py
Emma/emma_vis_libs/dataReports.py
Emma/emma_vis_libs/dataVisualiser.py
Emma/emma_vis_libs/dataVisualiserCategorisedSections.py
Emma/emma_vis_libs/dataVisualiserMemoryMap.py
Emma/emma_vis_libs/dataVisualiserObjects.py
Emma/emma_vis_libs/dataVisualiserSections.py
Emma/emma_vis_libs/helper.py
Emma/shared_libs/__init__.py
Emma/shared_libs/emma_helper.py
Emma/shared_libs/stringConstants.py
genDoc/_genCallGraphs.py
genDoc/_genUmlDiagrams.py
genDoc/genReadmeHtmlFromMd.py
tests/functional_tests/__init__.py
tests/functional_tests/test__cmd_line.py
tests/functional_tests/test__test_project.py
tests/other_files/__init__.py
tests/unit_tests/__init__.py
tests/unit_tests/test_FilePresenter.py
tests/unit_tests/test_configuration.py
tests/unit_tests/test_emma_helper.py
tests/unit_tests/test_memoryEntry.py
tests/unit_tests/test_memoryMap.py
tools/ghs-map-converter.py
pypiemma-4.0.1.dist-info/COPYING
pypiemma-4.0.1.dist-info/LICENSE
pypiemma-4.0.1.dist-info/METADATA
pypiemma-4.0.1.dist-info/WHEEL
pypiemma-4.0.1.dist-info/entry_points.txt
pypiemma-4.0.1.dist-info/top_level.txt
pypiemma-4.0.1.dist-info/RECORD
