Metadata-Version: 2.1
Name: pypiemma
Version: 4.0.1
Summary: Emma Memory and Mapfile Analyser (Emma) | Conduct static (i.e. worst case) memory consumption     analyses based on arbitrary linker map files. It produces extensive .csv files which are easy to filter and     post-process. Optionally .html and markdown reports as well as neat figures help you visualising your results.
Home-page: https://github.com/bmwcarit/Emma
Maintainer: The Emma Authors
Maintainer-email: emma-dev@googlegroups.com
License: GPLv3+
Keywords: memory-analysis,mapfile,memory-analyzer,embedded,ghs,gcc,mcu,linker,visualization,reports,csv,python,categorisation,memory-consumption,mapfile-analyser
Platform: UNKNOWN
Classifier: License :: OSI Approved :: GNU General Public License v3 or later (GPLv3+)
Classifier: Programming Language :: Python :: 3
Classifier: Operating System :: OS Independent
Classifier: Development Status :: 5 - Production/Stable
Classifier: Environment :: Console
Classifier: Topic :: Scientific/Engineering :: Visualization
Classifier: Topic :: Software Development
Classifier: Topic :: Software Development :: Embedded Systems
Classifier: Topic :: Software Development :: Quality Assurance
Requires-Python: >=3.6
Requires-Dist: Pygments
Requires-Dist: Markdown
Requires-Dist: matplotlib
Requires-Dist: pandas
Requires-Dist: pypiscout (>=2.0)
Requires-Dist: graphviz
Requires-Dist: svgwrite
Provides-Extra: dev
Requires-Dist: gprof2dot ; extra == 'dev'
Requires-Dist: pylint ; extra == 'dev'
Requires-Dist: mkdocs (>=1.1.2) ; extra == 'dev'
Requires-Dist: mkdocs-material (>=5.2.1) ; extra == 'dev'
